tikzfeynwrap/__init__.py
tikzfeynwrap/container.py
tikzfeynwrap/folder.py
tikzfeynwrap-0.0.9.dist-info/METADATA
tikzfeynwrap-0.0.9.dist-info/WHEEL
tikzfeynwrap-0.0.9.dist-info/top_level.txt
tikzfeynwrap-0.0.9.dist-info/RECORD
