Metadata-Version: 2.1
Name: tikzfeynwrap
Version: 0.0.9
Summary: Simple Wrapper for latex docker container
Home-page: https://github.com/npapapietro/tikzfeynwrap
Author: Nathan Papapietro <npapapietro95@gmail.com>
Author-email: npapapietro95@gmail.com
License: UNKNOWN
Platform: UNKNOWN
Classifier: Programming Language :: Python :: 3.7
Classifier: Programming Language :: Python :: 3.8
Classifier: Programming Language :: Python :: 3.9
Requires-Dist: docker (>=5.0.2)
Requires-Dist: ipython (>=7.27.0)
